{"data": {"ProZcSPTnCsGmKGcVhXkujlsZmeLfOGQEJK": {"date_expired": "2026-05-16 10:00:00.243017", "name": "Lariot", "status": "true"}, "ProshwZlTggoTuxfyppmqjGBvxEjioJRjJK": {"date_expired": "2026-05-26 13:50:39.057353", "name": "Horte", "status": "true", "tg": "all"}, "ProWaYXaXPAWNiNDOcwzddckNmlaPtMitJK": {"date_expired": "2026-08-06 20:23:25.879648", "name": "OPPO F5", "status": "true", "tg": "all"}, "ProEFOCaZDIwsiVbOMJCxwrVekQAIEwJEJK": {"date_expired": "2027-03-02 08:02:47.746542", "name": "TCL", "status": "true", "tg": "all"}, "ProWdhwairkCSckrqzCGZJrEJAQggKIyuJK": {"date_expired": "2026-04-03 13:31:56.161823", "name": "Erno", "tg": "false"}, "ProYtUhDMhepPDhzAUNRPkIfQVLTYpOtOJK": {"date_expired": "2026-04-04 10:44:45.824771", "name": "Flyx", "tg": "false"}, "ProQOentQWKrxwBIjnxziFhgxSOsOzSyAJK": {"date_expired": "2026-04-01 20:09:49.821162", "name": "An.El", "tg": "false"}, "ProEFMRFFWOqihfEkKCHPFDwYEPATEyfKJK": {"date_expired": "2026-04-01 20:10:31.480727", "name": "An.El2", "tg": "false"}, "ProgzDPWRHWVlZYmPgXhyIZilRjZenNRZJK": {"date_expired": "2026-04-01 20:10:44.349342", "name": "An.El3", "tg": "false"}, "ProgYaeSYceVqpDDFioOKspTynCvicyvQJK": {"date_expired": "2026-04-01 20:10:53.496506", "name": "An.El4", "tg": "false"}, "ProPeSCoMnMgSoVXLrmDFtqVorZkjLOHYJK": {"date_expired": "2026-04-01 20:23:44.407093", "name": "Nant's", "tg": "true"}, "ProwonKefdywRaNxgHWYaiMOPzqHrBkFzJK": {"date_expired": "2026-03-29 10:21:34.421693", "name": "Francesca", "tg": "false"}, "ProGeaGndEtjpkEiRfhMDOKIOfnSNrxykJK": {"date_expired": "2026-04-01 20:09:32.460677", "name": "An.El", "tg": "false"}, "ProAHfKbaVPACzoImBXaXgpEPKibPMUagJK": {"date_expired": "2026-04-03 19:08:30.043515", "name": "Arnaud", "tg": "false"}, "ProvRPGyZmYryidyoJBcLxOijYawydEqsJK": {"date_expired": "2026-03-31 21:13:39.981513", "name": "Tom Tom", "tg": "false"}, "ProAAcjQRKqIASTNickpRopYXUaXDhNhpJK": {"date_expired": "2026-03-31 19:59:08.242940", "name": "Sylvie", "tg": "true"}, "ProGAkaIvMOKqIneKfOkrQQReQYCpJKvbJK": {"date_expired": "2026-04-04 14:31:35.410543", "name": "Wendy", "tg": "false"}, "ProxSnygrIAWaetaOimvEmHrUJSUNyqApJK": {"date_expired": "2026-03-30 15:17:39.554089", "name": "David", "tg": "true"}, "ProkzIocBuoxFQeVXEmxRSXsGqPHnyKhpJK": {"date_expired": "2026-03-30 15:17:48.805502", "name": "David1", "tg": "true"}, "ProraCCbUTUXOhlFoTxZsqdcnPkVDTFcXJK": {"date_expired": "2026-03-30 17:02:11.081202", "name": "Nakym", "tg": "false"}, "ProHFWoWHvIJfBhznBNOfoRtALaHVXYgsJK": {"date_expired": "2026-03-30 17:11:50.939043", "name": "David2", "tg": "true"}, "ProPBlyBtbuclblpZNElpUWAwbxHTwVCBJK": {"date_expired": "2026-03-30 17:19:21.402362", "name": "Johnson", "tg": "false"}, "ProGzOHvIFRhZTZuTsARVIskWzxMuBoeHJK": {"date_expired": "2026-03-30 17:19:37.763176", "name": "Johnson1", "tg": "false"}, "PropIUNSLMwRSQXobVrNseNVWuBrMbCnHJK": {"date_expired": "2026-04-01 18:52:50.986567", "name": "Brunel", "tg": "false"}, "ProzUDyLJjcLHKHNunlpTaaqpQSvBTjzrJK": {"date_expired": "2026-03-30 17:48:27.063744", "name": "Njiva", "tg": "false"}, "ProiqvOggTAGJZHviLOadMcFKCqTUZNJPJK": {"date_expired": "2026-03-30 17:53:03.767958", "name": "Njiva1", "tg": "false"}, "ProBqfLOpJpPwIwCKlJqYpTwCGNvlyWNpJK": {"date_expired": "2026-03-30 19:39:13.583107", "name": "Noely", "tg": "false"}, "ProqGeMqPuLXPRhzuSJvmGvTwsIuEdFkSJK": {"date_expired": "2026-03-30 19:53:26.486349", "name": "Miarisoa", "tg": "false"}, "ProoLUvFBUibJmTEBFSFjUaakbeiVltyhJK": {"date_expired": "2026-03-30 19:58:28.691329", "name": "Tarcil", "tg": "false"}, "ProxEnLerzdzVQbYjmdPetnvfGVulmNllJK": {"date_expired": "2026-03-30 20:02:17.146398", "name": "Miarisoa", "tg": "false"}, "ProUbUBPiVtwtwElJCMTYZPTbQuPiAWYOJK": {"date_expired": "2026-03-30 20:14:52.977757", "name": "Romain", "tg": "false"}, "ProUeHkIFHWehHPgvdXMsGBOJoCeYjswoJK": {"date_expired": "2026-03-30 20:16:09.352550", "name": "Romain1", "tg": "false"}, "ProsXzSBfNDewaefmGYQElqfATnXcylMCJK": {"date_expired": "2026-03-30 22:06:27.419905", "name": "Tsaralaza", "tg": "false"}, "ProbIebfWxJXDKKOfMlilKmTiHWMtjPWTJK": {"date_expired": "2026-03-30 22:41:59.545770", "name": "Gerve", "tg": "false"}, "ProDsUiwnFIPolGfGMzcnHrvQWQQnqpIVJK": {"date_expired": "2026-03-31 06:21:16.568937", "name": "Pascal", "tg": "false"}, "ProNpjbgljJFAHEqSambHeEsbhumIdhKYJK": {"date_expired": "2026-03-31 08:05:35.081636", "name": "Antsa", "tg": "false"}, "ProZrzGevtECCaziUXmbXVNWhkZfMomIXJK": {"date_expired": "2026-03-31 15:17:29.366425", "name": "Faneva", "tg": "true"}, "ProouAIunGOvcJQuNZkHwzTMXHHUvbpNoJK": {"date_expired": "2026-03-31 09:16:43.046221", "name": "Ando Ny Avo", "tg": "false"}, "ProFyyvvLxeabOQOlSVDXmRnNiyGuESQoJK": {"date_expired": "2026-03-31 10:15:08.811539", "name": "Nambinina", "tg": "false"}, "ProrBUREBYIgHgecAqEAvQgFriJuxGulcJK": {"date_expired": "2026-03-31 16:44:56.371065", "name": "Amboara", "tg": "false"}, "ProyFOXeIJpkrxSorLGuvGtvKcIxjkWmnJK": {"date_expired": "2026-03-31 16:46:16.096788", "name": "Amboara1", "tg": "false"}, "ProWmYfEmSyfVgHSZRSVmjMZnWubKqjGNJK": {"date_expired": "2026-03-31 16:46:32.508068", "name": "Amboara", "tg": "false"}, "ProqLCQVhqRSxWaNVJWvtVmGGYeihTNNsJK": {"date_expired": "2026-03-31 16:46:49.404874", "name": "Amboara", "tg": "false"}, "ProtwxblZBlLLqlSsVLVwqCDrSsOWjNqDJK": {"date_expired": "2026-03-31 16:47:05.800468", "name": "Amboara", "tg": "false"}, "ProTyBjyLKhTjGMxwLKSfMriSRGTQYFXMJK": {"date_expired": "2026-03-31 20:06:37.242580", "name": "Mirana", "tg": "false"}, "ProagUyuNNQhoxWSglzzhcujCLzRRWnatJK": {"date_expired": "2026-03-31 20:11:43.882964", "name": "Hasina", "tg": "false"}, "ProFjTFsvPXKrKmbzjvGnOoIBURcwfKRVJK": {"date_expired": "2026-04-01 07:01:57.910715", "name": "Zafs", "tg": "false"}, "ProxaIeNNPGPsvgeJzDLkOMYSyKmAQrllJK": {"date_expired": "2026-03-30 08:19:19.114797", "name": "Nomeniavo", "tg": "true"}, "ProdEUqzVHTSFRUZIKGXRZEMdGybCbDzHJK": {"date_expired": "2026-03-27 08:30:43.387851", "name": "Kim Ka", "tg": "false"}, "ProzYWSePNKMpLFteqhIprEiFEYFxtocMJK": {"date_expired": "2026-03-31 10:21:58.704601", "name": "Niri kou", "tg": "false"}, "ProLiWkpcTWsygZEaQJHHXwkTEPTCbgMsJK": {"date_expired": "2026-04-01 12:13:14.200738", "name": "Na rindra", "tg": "false"}, "ProjlEUjECStlPqUHixdZGfOLUodGSnwdJK": {"date_expired": "2026-04-01 16:17:59.514555", "name": "Iarimalala", "tg": "false"}, "ProzONkvCLiyoKUDQPBtyELiPbCMwZPaqJK": {"date_expired": "2026-04-01 17:30:56.227301", "name": "Lalahy", "tg": "false"}, "ProqrJJObViyzbygMHyZyVgpnBBFrbQYjJK": {"date_expired": "2026-04-02 08:23:46.193112", "name": "Noel", "tg": "false"}, "ProdnWYPiNNsRRmgTcGEXaZNIPcYyHZGUJK": {"date_expired": "2026-04-02 15:02:09.310244", "name": "Mapyah", "tg": "false"}, "ProTVoIKwBCPkYuCzacmhjGBdmpUpjbwdJK": {"date_expired": "2026-04-02 15:41:47.338707", "name": "Njiva2", "tg": "false"}, "PronzFXXjxbpxgoktqBaRdZLaMqzyIlCjJK": {"date_expired": "2026-04-02 18:26:07.386297", "name": "Fredi", "tg": "false"}, "ProIcIThWSHHUPSkGEmVIsLjXVpkSasLIJK": {"date_expired": "2026-04-01 20:20:20.701791", "name": "Ramaroson", "tg": "true"}, "ProCTfQVVrRFSeUWSDQvcRwgSjdleAzyEJK": {"date_expired": "2026-04-03 07:34:07.555539", "name": "Sarobidy", "tg": "false"}, "ProwZNraGxXExPGMhpWbPXapQKgEdvsevJK": {"date_expired": "2026-04-03 08:34:27.021353", "name": "Mahefason", "tg": "false"}, "ProMzdBfLZNCisMvikYiSKsDcOrcoKfORJK": {"date_expired": "2026-04-02 09:04:30.862798", "name": "Gladys", "tg": "false"}, "ProTMicZOQxZTMluTnJiGJbTjcvmNlieyJK": {"date_expired": "2026-03-31 09:33:30.292568", "name": "Felana", "tg": "false"}, "ProMjBmXsqTiJgvaaQNRsGyHHeBRevzqDJK": {"date_expired": "2026-03-30 18:22:54.182797", "name": "Victorinz", "tg": "false"}, "ProSikVHWcCPfBzLdcTeuCRuioiKRvewmJK": {"date_expired": "2026-03-31 22:46:49.610003", "name": "Amboaravaovao", "tg": "false"}, "ProCvfmLsaxaCQTZABlPduCoFWQUftxOcJK": {"date_expired": "2026-04-04 05:44:52.379084", "name": "Gerve1", "tg": "false"}, "ProJxQkiDQnngNDeelmgOYGUgJEoNLLVnJK": {"date_expired": "2026-03-29 09:01:56.379048", "name": "Faralahy1joursftsn", "tg": "false"}, "ProBoyMfYEXqODHCtbmSfDTdHeszMYSALJK": {"date_expired": "2026-04-04 10:45:12.747304", "name": "Donnatien", "tg": "false"}, "ProZjSYBeCGWdHGFGMBKBiQKNQnkbPOplJK": {"date_expired": "2026-04-03 15:56:27.144541", "name": "Namby", "tg": "false"}, "ProkeNqujkzlSkQNtvjXKmydKOpAFxkmNJK": {"date_expired": "2026-04-05 13:03:07.147695", "name": "Bien Venu", "tg": "false"}, "ProZDVRaxaNaqZCFPbEGvwApbjTpNBqwRJK": {"date_expired": "2026-04-03 14:37:02.837058", "name": "Emmanuel", "tg": "false"}, "ProeeEVTDbxFGEudAEYWDDMIIFANaVBXYJK": {"date_expired": "2026-04-05 17:35:09.865762", "name": "Nant's", "tg": "false"}, "ProxVLBDhkcmNMNEQRYErztBLUzODPDKfJK": {"date_expired": "2026-04-05 17:38:05.344185", "name": "Dennery", "tg": "false"}, "ProfJJNLCmRbhMklTKUMZlkgUgiCuLRniJK": {"date_expired": "2026-04-05 18:17:21.040263", "name": "Rayan", "tg": "false"}, "ProijJkNxjDJWPzszpOLfjBNVSBxOmqGsJK": {"date_expired": "2026-04-05 18:30:02.423678", "name": "Evalin", "tg": "false"}}, "annonce": "Salama daholo\ud83d\ude0a\nHialana tsiny t@ ilay maj teo aloha ireny @ilay resaka captcha tsy mety\ud83d\ude4f\nEfa misy maj 6.8 ao izao\u2705\nEfa tokony tsy blem tsony le resaka captcha ka manasa anareo anao maj daholo\ud83d\ude4f"}